qssp/__init__.py
qssp/hmm.py
qssp/logistics.txt
qssp/q_objects.py
qssp/qshmm.py
qssp/utils.py
qssp/viz.py
qssp-0.0.1.dist-info/METADATA
qssp-0.0.1.dist-info/WHEEL
qssp-0.0.1.dist-info/licenses/LICENSE.txt
qssp-0.0.1.dist-info/RECORD
